{"url": {"canonical": "https://www.economist.com/europe/2024/02/28/is-europes-lack-of-skyscapers-a-blessing-or-a-sign-of-deficient-ambition", "__typename": "URL"}, "__typename": "Content", "id": "/content/3n1gbd1p1akeb02nlhd7vn4a9aomq3q1", "tegID": "3n1gbd1p1akeb02nlhd7vn4a9aomq3q1", "type": ["Article", "NewsArticle", "AnalysisNewsArticle"], "headline": "Is Europe\u2019s stubby skyline a sign of low ambition?", "subheadline": "Charlemagne", "seoPageTitle": null, "seoMetadataDescription": null, "ad": {"grapeshot": {"channels": [{"name": "gv_safe", "score": 34319.777, "__typename": "GrapeshotChannel"}, {"name": "gb_safe", "score": 6.683, "__typename": "GrapeshotChannel"}, {"name": "gb_safe_from_high", "score": 6.683, "__typename": "GrapeshotChannel"}, {"name": "gb_safe_from_high_med", "score": 6.683, "__typename": "GrapeshotChannel"}, {"name": "pos_israel-hamas_war", "score": 6.683, "__typename": "GrapeshotChannel"}, {"name": "gs_science", "score": 6.671, "__typename": "GrapeshotChannel"}, {"name": "gs_science_geography", "score": 5.835, "__typename": "GrapeshotChannel"}, {"name": "gs_busfin", "score": 4.4, "__typename": "GrapeshotChannel"}, {"name": "gs_business", "score": 3.589, "__typename": "GrapeshotChannel"}, {"name": "gs_busfin_indus", "score": 3.585, "__typename": "GrapeshotChannel"}, {"name": "gs_busfin_indus_construction", "score": 3.393, "__typename": "GrapeshotChannel"}, {"name": "gs_business_construction", "score": 3.393, "__typename": "GrapeshotChannel"}, {"name": "neg_omd_exclusion", "score": 1.464, "__typename": "GrapeshotChannel"}, {"name": "neg_cop28", "score": 1.295, "__typename": "GrapeshotChannel"}, {"name": "cigna_healthyhybridworkplace", "score": 1.176, "__typename": "GrapeshotChannel"}, {"name": "gs_tech", "score": 1.122, "__typename": "GrapeshotChannel"}, {"name": "gs_tech_compute", "score": 1.122, "__typename": "GrapeshotChannel"}, {"name": "gs_home", "score": 1.12, "__typename": "GrapeshotChannel"}, {"name": "gs_home_property", "score": 1.12, "__typename": "GrapeshotChannel"}, {"name": "eastern_europe", "score": 1.106, "__typename": "GrapeshotChannel"}, {"name": "neg_exxon", "score": 1.066, "__typename": "GrapeshotChannel"}, {"name": "america_department_commerce", "score": 1.065, "__typename": "GrapeshotChannel"}, {"name": "cigna_puttingfamilyfirst", "score": 1.048, "__typename": "GrapeshotChannel"}, {"name": "ibm_blacklist", "score": 1.038, "__typename": "GrapeshotChannel"}, {"name": "fidelity_blacklist", "score": 0.978, "__typename": "GrapeshotChannel"}, {"name": "gs_realestate", "score": 0.968, "__typename": "GrapeshotChannel"}], "__typename": "Grapeshot"}, "__typename": "Ad"}, "audio": {"main": {"url": {"canonical": "https://www.economist.com/media-assets/audio/042%20Europe%20-%20Charlemagne-3b253a542a0e51b288db45a37ce1e229.mp3", "__typename": "URL"}, "__typename": "Content", "duration": "7:27", "hasPart": {"parts": [{"podcastLocked": false, "headline": "Is Europe\u2019s stubby skyline a sign of low ambition?", "datePublished": "2024-02-28T19:25:20Z", "publication": [{"type": ["PublicationIssue"], "headline": "WEEKLY EDITION: MAR 2ND 2024", "podcastImage": "", "keyword": [], "podcastSlug": "", "__typename": "Content"}, {"type": ["PublicationIssue", "RegionalIssue"], "headline": "WEEKLY EDITION: MAR 2ND 2024", "podcastImage": "", "keyword": [], "podcastSlug": "", "__typename": "Content"}, {"type": ["PublicationIssue", "RegionalIssue"], "headline": "WEEKLY EDITION: MAR 2ND 2024", "podcastImage": "", "keyword": [], "podcastSlug": "", "__typename": "Content"}, {"type": ["PublicationIssue", "RegionalIssue"], "headline": "WEEKLY EDITION: MAR 2ND 2024", "podcastImage": "", "keyword": [], "podcastSlug": "", "__typename": "Content"}, {"type": ["PublicationIssue", "RegionalIssue"], "headline": "WEEKLY EDITION: MAR 2ND 2024", "podcastImage": "", "keyword": [], "podcastSlug": "", "__typename": "Content"}, {"type": ["PublicationIssue", "RegionalIssue"], "headline": "WEEKLY EDITION: MAR 2ND 2024", "podcastImage": "", "keyword": [], "podcastSlug": "", "__typename": "Content"}, {"type": ["PublicationIssue", "RegionalIssue"], "headline": "WEEKLY EDITION: MAR 2ND 2024", "podcastImage": "", "keyword": [], "podcastSlug": "", "__typename": "Content"}, {"type": ["PublicationIssue", "RegionalIssue"], "headline": "WEEKLY EDITION: MAR 2ND 2024", "podcastImage": "", "keyword": [], "podcastSlug": "", "__typename": "Content"}], "__typename": "Content"}], "__typename": "HasPart"}}, "__typename": "Media"}, "image": {"main": {"url": {"canonical": "https://www.economist.com/media-assets/image/20240302_EUD000.jpg", "__typename": "URL"}, "__typename": "Content", "height": 720, "width": 1280, "description": "A person at the top of a church tower shakes their fist at a row of skyscrapers on the horizon"}, "promo": null, "__typename": "Media"}, "description": "Only seven of the world\u2019s 1,000 tallest buildings are in the EU", "datePublished": "2024-02-28T19:25:20Z", "dateModified": "2024-02-29T19:08:32Z", "dateRevised": "", "dateRevisedString": "", "datePublishedString": "Feb 28th 2024", "dateCreated": "2024-02-28T14:23:22Z", "copyrightYear": 2024, "inLanguage": "en", "byline": "", "dateline": null, "topic": null, "text": [{"type": "tag", "name": "p", "attribs": {}, "children": [{"type": "tag", "name": "span", "attribs": {"data-caps": "initial"}, "children": [{"data": "A", "type": "text"}]}, {"type": "tag", "name": "small", "attribs": {}, "children": [{"data": "top an ordinary ", "type": "text"}]}, {"data": "slab of office building in downtown ", "type": "text"}, {"type": "tag", "name": "a", "attribs": {"href": "https://www.economist.com/the-economist-explains/2024/01/30/what-on-earth-is-happening-in-poland"}, "children": [{"data": "Warsaw", "type": "text"}]}, {"data": " juts what at first might look like yet another example of architectural one-upmanship. But the 80-metre steel spire pointing out of the newish Varso tower is not there merely to provide bragging rights to the building\u2019s owners. For over six decades until Varso was completed in 2022, the tallest building in Poland had been a monumental \u201cgift\u201d from ", "type": "text"}, {"type": "tag", "name": "a", "attribs": {"href": "https://www.economist.com/culture/2023/11/28/in-russias-arsenal-the-knife-and-fork-have-been-powerful-weapons"}, "children": [{"data": "Joseph Stalin", "type": "text"}]}, {"data": ", a tribute to unrequited communist amity completed two years after the dictator\u2019s death in 1953. Without its pointy appendage the new edifice\u2014a tribute to capitalism just one city block away from the enduring Soviet monolith\u2014would have fallen a few centimetres short. Standing proud at 310 metres including its spire, Varso thus holds the title of tallest occupied building not just in the city but in the whole ", "type": "text"}, {"type": "tag", "name": "small", "attribs": {}, "children": [{"data": "EU", "type": "text"}]}, {"data": ". ", "type": "text"}]}, {"type": "tag", "name": "p", "attribs": {}, "children": [{"data": "Those hoping to glimpse a marvel of architecture and engineering are in for a disappointment: Varso and its 53 floors would be difficult to spot in the thicket of skyscrapers found in Manhattan, Shanghai or Dubai these days. Even with its height-enhancing spire the Polish edifice is but the 172nd tallest building in the world, according to the tower-spotters at the Council on Tall Buildings and Urban Habitat (", "type": "text"}, {"type": "tag", "name": "small", "attribs": {}, "children": [{"data": "CTBUH", "type": "text"}]}, {"data": "), based in Chicago. Continental Europe\u2019s second-tallest tower does not make the global top 500; in the year Varso was completed seven skyscrapers went up in America, China, Indonesia and Kazakhstan that would overshadow it. Once an American phenomenon, high-rises have long since become a global one. Everywhere is building upwards, higher, further into the sky\u2014except Europe. At least outside the continent\u2019s fringes in London, Istanbul and Moscow, it is the peninsula that tower-builders forgot. Both North and South America, Asia, Oceania and soon Africa all have more buildings of 250 metres or higher. Only seven of the world\u2019s tallest 1,000 buildings are in the ", "type": "text"}, {"type": "tag", "name": "small", "attribs": {}, "children": [{"data": "EU", "type": "text"}]}, {"data": ".", "type": "text"}]}, {"type": "tag", "name": "p", "attribs": {}, "children": [{"data": "And long may that remain the case, many might say. What would Rome or Prague want with such outsize erections? A continent of piazzas and tree-lined boulevards needs no such monuments to the Trumpian egos of developers. Yet Europe\u2019s reticence even when it comes to shorter scrapers is notable. As a rich place with scarce land and lots of people\u2014Germany has a higher population density than the tower-mad United Arab Emirates\u2014Europe might have been expected to join the tower-builders. For those who see skyscrapers as a symbol of progress and ambition, this once again looks like the signal of a continent that has given up.", "type": "text"}]}, {"type": "tag", "name": "p", "attribs": {}, "children": [{"data": "The obvious reason for Europe\u2019s low-rise skylines is its stringent planning and heritage rules. Tall buildings sprouted in America in the late 19th century thanks to developments in the steel frames needed to build them and lifts to get people to their upper floors. Europe had the skills to deploy these\u2014Gustave Eiffel knew a thing or two about metal structures, and Werner von Siemens about lifts\u2014but by then its major cities already had rich neighbourhoods worth preserving. The density that American wannabe metropolises sought to create with skyscrapers already existed in the compact warren of streets that make up European cities. ", "type": "text"}]}, {"type": "tag", "name": "p", "attribs": {}, "children": [{"data": "It did not help that the high-rises Europe built often turned out poorly. In many countries the first towers were shabby public-housing projects, which dented the prestige of tall buildings. Rotterdam (\u201cManhattan on the Maas\u201d) and Frankfurt (\u201cMainhattan\u201d), two places with towers more modest than the nicknames might suggest, are on few tourists\u2019 itineraries. In Paris the Tour Montparnasse was considered so hideous after it was completed in 1973 that restrictions were introduced limiting buildings in the city to just 37 metres. Only in the business-district suburb of La D\u00e9fense did tall buildings pop up\u2014albeit at a third the size of what Chinese or Emirati developers go for these days. \u201cAmerica builds its towers in the centre,\u201d says Daniel Safarik of the ", "type": "text"}, {"type": "tag", "name": "small", "attribs": {}, "children": [{"data": "CTBUH", "type": "text"}]}, {"data": ". \u201cFor Europe, they are more often something you stick in the periphery.\u201d Out of sight, were they not so tall, and out of mind.", "type": "text"}]}, {"type": "tag", "name": "p", "attribs": {}, "children": [{"data": "Europe\u2019s distinctive geography and economy play their part too. Given its northerly latitude, the views of the 1% atop skyscrapers come at the cost of more shade for the rest. The 245-metre Karlatornet currently under construction in Sweden will create a shadow at mid-afternoon roughly the same length as the Burj Khalifa in Dubai, the world\u2019s tallest building at 828 metres. A continent split into dozens of smallish countries resulted in few cities big enough to justify tall buildings: none of the world\u2019s biggest 25 metropolises are in Europe. Many skyscrapers globally were named after companies that sought the cachet that came with height, like the Sears tower in Chicago or the Chrysler building in New York City. Europe has relatively few such corporate giants. ", "type": "text"}]}, {"type": "tag", "name": "h2", "attribs": {}, "children": [{"data": "Castles in the sky", "type": "text"}]}, {"type": "tag", "name": "p", "attribs": {}, "children": [{"data": "The most recent burst of skyscrapers has involved status symbols in Asia. Developers in China and the Emirates vied to build higher in a bid to put second-tier cities on the map. Europe may justifiably feel it is above such games. \u201cFrance does not need the tallest building in the world to be recognisable,\u201d says Dario Trabucco at the University of Venice. Another new fad is residential skyscrapers of the sort that now line Central Park in Manhattan. These are designed for the global ", "type": "text"}, {"type": "tag", "name": "i", "attribs": {}, "children": [{"data": "nouveau riche", "type": "text"}]}, {"data": ", often from far afield. Europe is more of an old-money kind of place. Why move to the top of a glass tower when the family ", "type": "text"}, {"type": "tag", "name": "i", "attribs": {}, "children": [{"data": "palazzo ", "type": "text"}]}, {"data": "does the trick nicely?", "type": "text"}]}, {"type": "tag", "name": "p", "attribs": {}, "children": [{"data": "Europe is no architectural sloth. But it has focused on making existing places better rather than colonising the urban sky. In short: more cycle lanes, fewer penthouses. It finds its architectural kicks in other ways: the pyramid in the courtyard of the Louvre and the glass dome atop the German Reichstag are no less ambitious than anything knocked up in Dubai or Taipei. That Europe has known how to build high\u2014but chosen not to\u2014is visible to anybody who has visited Paris. The Eiffel Tower, built in 1889, has too little occupiable space to be considered a proper building. Still, it stands 20 metres higher than the top of Varso\u2019s spire. ", "type": "text"}, {"type": "tag", "name": "span", "attribs": {"data-ornament": "ufinish"}, "children": [{"data": "\u25a0", "type": "text"}]}]}, {"type": "tag", "name": "p", "attribs": {}, "children": [{"type": "tag", "name": "b", "attribs": {}, "children": [{"data": "Read more from Charlemagne, our columnist on European politics: ", "type": "text"}]}, {"type": "tag", "name": "br", "attribs": {}, "children": []}, {"type": "tag", "name": "i", "attribs": {}, "children": [{"type": "tag", "name": "a", "attribs": {"href": "https://www.economist.com/europe/2024/02/22/europes-generosity-to-ukrainian-refugees-is-not-so-welcome-in-ukraine"}, "children": [{"data": "Europe\u2019s generosity to Ukrainian refugees is not so welcome\u2014in Ukraine", "type": "text"}]}, {"data": " (Feb 22nd)", "type": "text"}]}, {"type": "tag", "name": "br", "attribs": {}, "children": []}, {"type": "tag", "name": "i", "attribs": {}, "children": [{"type": "tag", "name": "a", "attribs": {"href": "https://www.economist.com/europe/2024/02/15/how-not-to-botch-the-upcoming-eu-leadership-reshuffle", "data-tegid": "t1v3de4nelt9qr9l7ee61un41v7gcr5n"}, "children": [{"data": "How not to botch the upcoming EU leadership reshuffle", "type": "text"}]}, {"data": " (Feb 14th)", "type": "text"}]}, {"type": "tag", "name": "br", "attribs": {}, "children": []}, {"type": "tag", "name": "i", "attribs": {}, "children": [{"type": "tag", "name": "a", "attribs": {"href": "https://www.economist.com/europe/2024/02/08/europe-is-importing-a-solar-boom-good-news-for-nearly-everyone"}, "children": [{"data": "Europe is importing a solar boom. Good news for (nearly) everyone", "type": "text"}]}, {"data": " (Feb 8th)", "type": "text"}]}]}, {"type": "tag", "name": "p", "attribs": {}, "children": [{"type": "tag", "name": "i", "attribs": {}, "children": [{"data": "Also: How the Charlemagne column ", "type": "text"}, {"type": "tag", "name": "a", "attribs": {"href": "https://www.economist.com/column-names"}, "children": [{"data": "got its name", "type": "text"}]}]}]}, {"type": "tag", "name": "p", "attribs": {}, "children": [{"type": "tag", "name": "i", "attribs": {}, "children": [{"data": "To stay on top of the biggest European stories, sign up to ", "type": "text"}, {"type": "tag", "name": "a", "attribs": {"href": "https://www.economist.com/newsletters/cafe-europa"}, "children": [{"data": "Caf\u00e9 Europa", "type": "text"}]}, {"data": ", our weekly subscriber-only newsletter.", "type": "text"}]}]}], "about": {"public": null, "__typename": "Taxonomies"}, "print": {"headline": "Where are Europe\u2019s towers?", "section": {"url": {"canonical": "https://www.economist.com/europe/", "__typename": "URL"}, "__typename": "Content", "headline": "Europe"}, "__typename": "Print"}, "contentIdentity": {"articleType": null, "mediaType": null, "__typename": "ContentIdentity"}, "articleSection": {"public": null, "internal": [{"url": {"canonical": "https://www.economist.com/europe/", "__typename": "URL"}, "__typename": "Content", "id": "/content/75ks360ifh4d6k3c3n17b7s7uqcvb61a", "tegID": "75ks360ifh4d6k3c3n17b7s7uqcvb61a", "headline": "Europe", "hasPart": {"parts": [{"url": {"canonical": "https://www.economist.com/europe/2024/02/29/france-and-germany-are-at-loggerheads-over-military-aid-to-ukraine", "__typename": "URL"}, "__typename": "Content", "id": "/content/2ggkfs0jmaoto8455v6kp9j3dngkdpvb", "type": ["Article", "NewsArticle", "AnalysisNewsArticle"], "contentIdentity": {"mediaType": null, "articleType": null, "__typename": "ContentIdentity"}, "articleSection": {"internal": [{"url": {"canonical": "https://www.economist.com/europe/", "__typename": "URL"}, "__typename": "Content", "headline": "Europe", "tegID": "75ks360ifh4d6k3c3n17b7s7uqcvb61a"}], "__typename": "Taxonomies"}, "publication": [{"headline": "WEEKLY EDITION: MAR 2ND 2024", "url": {"canonical": "https://www.economist.com/printedition/2024-03-02", "__typename": "URL"}, "__typename": "Content", "tegID": "j719mr4brfrmovgpemhjfldmmo3cg353"}, {"headline": "WEEKLY EDITION: MAR 2ND 2024", "url": {"canonical": "https://www.economist.com/eu/printedition/2024-03-02", "__typename": "URL"}, "__typename": "Content", "tegID": "c8e03oqtmf88qosaeavni6do2b3qp7t4"}, {"headline": "WEEKLY EDITION: MAR 2ND 2024", "url": {"canonical": "https://www.economist.com/ap/printedition/2024-03-02", "__typename": "URL"}, "__typename": "Content", "tegID": "jhnack3g4lmfqld87qn5qkj9v0m5h8qc"}, {"headline": "WEEKLY EDITION: MAR 2ND 2024", "url": {"canonical": "https://www.economist.com/la/printedition/2024-03-02", "__typename": "URL"}, "__typename": "Content", "tegID": "3l7slvo89iioeimngqiosm3ogebqdknv"}, {"headline": "WEEKLY EDITION: MAR 2ND 2024", "url": {"canonical": "https://www.economist.com/me/printedition/2024-03-02", "__typename": "URL"}, "__typename": "Content", "tegID": "i8cbko3s9k1rftrspvilocug59dv5ou6"}, {"headline": "WEEKLY EDITION: MAR 2ND 2024", "url": {"canonical": "https://www.economist.com/uk/printedition/2024-03-02", "__typename": "URL"}, "__typename": "Content", "tegID": "nphn7628rfcto0pgpeg2gce0e023fm7h"}, {"headline": "WEEKLY EDITION: MAR 2ND 2024", "url": {"canonical": "https://www.economist.com/na/printedition/2024-03-02", "__typename": "URL"}, "__typename": "Content", "tegID": "reeoom14ks2v3cnlekl593kvrldi9kak"}, {"headline": "WEEKLY EDITION: MAR 2ND 2024", "url": {"canonical": "https://www.economist.com/a/printedition/2024-03-02", "__typename": "URL"}, "__typename": "Content", "tegID": "5ga9s0u1etdqmbcbmos3rp9tudhevom8"}], "channel": {"tegID": "j53t6hsedat4l7rkbb1le98u73262sh5", "__typename": "Content"}, "headline": "France and Germany are at loggerheads over military aid to Ukraine", "subheadline": "Friendly fire", "datePublished": "2024-02-29T14:02:10Z", "description": "A summit in France made things worse", "image": {"main": {"url": {"canonical": "https://www.economist.com/media-assets/image/20240302_EUP503.jpg", "__typename": "URL"}, "__typename": "Content", "width": 1280, "height": 720}, "__typename": "Media", "promo": null}}, {"url": {"canonical": "https://www.economist.com/europe/2024/02/29/europe-hopes-barbed-wire-will-keep-migrants-out-it-wont", "__typename": "URL"}, "__typename": "Content", "id": "/content/4l5n9rquk0j0r4ak2qrchn772fks2oue", "type": ["Article", "NewsArticle", "AnalysisNewsArticle"], "contentIdentity": {"mediaType": null, "articleType": null, "__typename": "ContentIdentity"}, "articleSection": {"internal": [{"url": {"canonical": "https://www.economist.com/europe/", "__typename": "URL"}, "__typename": "Content", "headline": "Europe", "tegID": "75ks360ifh4d6k3c3n17b7s7uqcvb61a"}], "__typename": "Taxonomies"}, "publication": [{"headline": "WEEKLY EDITION: MAR 2ND 2024", "url": {"canonical": "https://www.economist.com/printedition/2024-03-02", "__typename": "URL"}, "__typename": "Content", "tegID": "j719mr4brfrmovgpemhjfldmmo3cg353"}, {"headline": "WEEKLY EDITION: MAR 2ND 2024", "url": {"canonical": "https://www.economist.com/eu/printedition/2024-03-02", "__typename": "URL"}, "__typename": "Content", "tegID": "c8e03oqtmf88qosaeavni6do2b3qp7t4"}, {"headline": "WEEKLY EDITION: MAR 2ND 2024", "url": {"canonical": "https://www.economist.com/ap/printedition/2024-03-02", "__typename": "URL"}, "__typename": "Content", "tegID": "jhnack3g4lmfqld87qn5qkj9v0m5h8qc"}, {"headline": "WEEKLY EDITION: MAR 2ND 2024", "url": {"canonical": "https://www.economist.com/la/printedition/2024-03-02", "__typename": "URL"}, "__typename": "Content", "tegID": "3l7slvo89iioeimngqiosm3ogebqdknv"}, {"headline": "WEEKLY EDITION: MAR 2ND 2024", "url": {"canonical": "https://www.economist.com/me/printedition/2024-03-02", "__typename": "URL"}, "__typename": "Content", "tegID": "i8cbko3s9k1rftrspvilocug59dv5ou6"}, {"headline": "WEEKLY EDITION: MAR 2ND 2024", "url": {"canonical": "https://www.economist.com/uk/printedition/2024-03-02", "__typename": "URL"}, "__typename": "Content", "tegID": "nphn7628rfcto0pgpeg2gce0e023fm7h"}, {"headline": "WEEKLY EDITION: MAR 2ND 2024", "url": {"canonical": "https://www.economist.com/na/printedition/2024-03-02", "__typename": "URL"}, "__typename": "Content", "tegID": "reeoom14ks2v3cnlekl593kvrldi9kak"}, {"headline": "WEEKLY EDITION: MAR 2ND 2024", "url": {"canonical": "https://www.economist.com/a/printedition/2024-03-02", "__typename": "URL"}, "__typename": "Content", "tegID": "5ga9s0u1etdqmbcbmos3rp9tudhevom8"}], "channel": {"tegID": "j53t6hsedat4l7rkbb1le98u73262sh5", "__typename": "Content"}, "headline": "Europe hopes barbed wire will keep migrants out. It won\u2019t", "subheadline": "Get off the fence", "datePublished": "2024-02-29T14:02:06Z", "description": "Politicians feel compelled to respond to voters\u2019 concerns", "image": {"main": {"url": {"canonical": "https://www.economist.com/media-assets/image/20240302_EUP504.jpg", "__typename": "URL"}, "__typename": "Content", "width": 1280, "height": 720}, "__typename": "Media", "promo": null}}, {"url": {"canonical": "https://www.economist.com/europe/2024/02/29/azerbaijan-is-racing-to-rebuild-in-recaptured-nagorno-karabakh", "__typename": "URL"}, "__typename": "Content", "id": "/content/prq002j35qkrc5lrqpkgrmk8lfjpmpc6", "type": ["Article", "NewsArticle", "AnalysisNewsArticle"], "contentIdentity": {"mediaType": null, "articleType": null, "__typename": "ContentIdentity"}, "articleSection": {"internal": [{"url": {"canonical": "https://www.economist.com/europe/", "__typename": "URL"}, "__typename": "Content", "headline": "Europe", "tegID": "75ks360ifh4d6k3c3n17b7s7uqcvb61a"}], "__typename": "Taxonomies"}, "publication": [{"headline": "WEEKLY EDITION: MAR 2ND 2024", "url": {"canonical": "https://www.economist.com/printedition/2024-03-02", "__typename": "URL"}, "__typename": "Content", "tegID": "j719mr4brfrmovgpemhjfldmmo3cg353"}, {"headline": "WEEKLY EDITION: MAR 2ND 2024", "url": {"canonical": "https://www.economist.com/eu/printedition/2024-03-02", "__typename": "URL"}, "__typename": "Content", "tegID": "c8e03oqtmf88qosaeavni6do2b3qp7t4"}, {"headline": "WEEKLY EDITION: MAR 2ND 2024", "url": {"canonical": "https://www.economist.com/ap/printedition/2024-03-02", "__typename": "URL"}, "__typename": "Content", "tegID": "jhnack3g4lmfqld87qn5qkj9v0m5h8qc"}, {"headline": "WEEKLY EDITION: MAR 2ND 2024", "url": {"canonical": "https://www.economist.com/la/printedition/2024-03-02", "__typename": "URL"}, "__typename": "Content", "tegID": "3l7slvo89iioeimngqiosm3ogebqdknv"}, {"headline": "WEEKLY EDITION: MAR 2ND 2024", "url": {"canonical": "https://www.economist.com/me/printedition/2024-03-02", "__typename": "URL"}, "__typename": "Content", "tegID": "i8cbko3s9k1rftrspvilocug59dv5ou6"}, {"headline": "WEEKLY EDITION: MAR 2ND 2024", "url": {"canonical": "https://www.economist.com/uk/printedition/2024-03-02", "__typename": "URL"}, "__typename": "Content", "tegID": "nphn7628rfcto0pgpeg2gce0e023fm7h"}, {"headline": "WEEKLY EDITION: MAR 2ND 2024", "url": {"canonical": "https://www.economist.com/na/printedition/2024-03-02", "__typename": "URL"}, "__typename": "Content", "tegID": "reeoom14ks2v3cnlekl593kvrldi9kak"}, {"headline": "WEEKLY EDITION: MAR 2ND 2024", "url": {"canonical": "https://www.economist.com/a/printedition/2024-03-02", "__typename": "URL"}, "__typename": "Content", "tegID": "5ga9s0u1etdqmbcbmos3rp9tudhevom8"}], "channel": {"tegID": "j53t6hsedat4l7rkbb1le98u73262sh5", "__typename": "Content"}, "headline": "Azerbaijan is racing to rebuild in recaptured Nagorno-Karabakh", "subheadline": "After the war", "datePublished": "2024-02-29T14:02:04Z", "description": "Exiled Azeris are returning", "image": {"main": {"url": {"canonical": "https://www.economist.com/media-assets/image/20240302_EUP505.jpg", "__typename": "URL"}, "__typename": "Content", "width": 1280, "height": 720}, "__typename": "Media", "promo": null}}, {"url": {"canonical": "https://www.economist.com/europe/2024/02/28/is-europes-lack-of-skyscapers-a-blessing-or-a-sign-of-deficient-ambition", "__typename": "URL"}, "__typename": "Content", "id": "/content/3n1gbd1p1akeb02nlhd7vn4a9aomq3q1", "type": ["Article", "NewsArticle", "AnalysisNewsArticle"], "contentIdentity": {"mediaType": null, "articleType": null, "__typename": "ContentIdentity"}, "articleSection": {"internal": [{"url": {"canonical": "https://www.economist.com/europe/", "__typename": "URL"}, "__typename": "Content", "headline": "Europe", "tegID": "75ks360ifh4d6k3c3n17b7s7uqcvb61a"}], "__typename": "Taxonomies"}, "publication": [{"headline": "WEEKLY EDITION: MAR 2ND 2024", "url": {"canonical": "https://www.economist.com/printedition/2024-03-02", "__typename": "URL"}, "__typename": "Content", "tegID": "j719mr4brfrmovgpemhjfldmmo3cg353"}, {"headline": "WEEKLY EDITION: MAR 2ND 2024", "url": {"canonical": "https://www.economist.com/eu/printedition/2024-03-02", "__typename": "URL"}, "__typename": "Content", "tegID": "c8e03oqtmf88qosaeavni6do2b3qp7t4"}, {"headline": "WEEKLY EDITION: MAR 2ND 2024", "url": {"canonical": "https://www.economist.com/ap/printedition/2024-03-02", "__typename": "URL"}, "__typename": "Content", "tegID": "jhnack3g4lmfqld87qn5qkj9v0m5h8qc"}, {"headline": "WEEKLY EDITION: MAR 2ND 2024", "url": {"canonical": "https://www.economist.com/la/printedition/2024-03-02", "__typename": "URL"}, "__typename": "Content", "tegID": "3l7slvo89iioeimngqiosm3ogebqdknv"}, {"headline": "WEEKLY EDITION: MAR 2ND 2024", "url": {"canonical": "https://www.economist.com/me/printedition/2024-03-02", "__typename": "URL"}, "__typename": "Content", "tegID": "i8cbko3s9k1rftrspvilocug59dv5ou6"}, {"headline": "WEEKLY EDITION: MAR 2ND 2024", "url": {"canonical": "https://www.economist.com/uk/printedition/2024-03-02", "__typename": "URL"}, "__typename": "Content", "tegID": "nphn7628rfcto0pgpeg2gce0e023fm7h"}, {"headline": "WEEKLY EDITION: MAR 2ND 2024", "url": {"canonical": "https://www.economist.com/na/printedition/2024-03-02", "__typename": "URL"}, "__typename": "Content", "tegID": "reeoom14ks2v3cnlekl593kvrldi9kak"}, {"headline": "WEEKLY EDITION: MAR 2ND 2024", "url": {"canonical": "https://www.economist.com/a/printedition/2024-03-02", "__typename": "URL"}, "__typename": "Content", "tegID": "5ga9s0u1etdqmbcbmos3rp9tudhevom8"}], "channel": {"tegID": "j53t6hsedat4l7rkbb1le98u73262sh5", "__typename": "Content"}, "headline": "Is Europe\u2019s stubby skyline a sign of low ambition?", "subheadline": "Charlemagne", "datePublished": "2024-02-28T19:25:20Z", "description": "Only seven of the world\u2019s 1,000 tallest buildings are in the EU", "image": {"main": {"url": {"canonical": "https://www.economist.com/media-assets/image/20240302_EUD000.jpg", "__typename": "URL"}, "__typename": "Content", "width": 1280, "height": 720}, "__typename": "Media", "promo": null}}, {"url": {"canonical": "https://www.economist.com/europe/2024/02/26/kharkiv-is-struggling-under-russian-rocket-attacks", "__typename": "URL"}, "__typename": "Content", "id": "/content/pc80jb0n782a5lmmoifjssujpmp6osr8", "type": ["Article", "NewsArticle", "AnalysisNewsArticle"], "contentIdentity": {"mediaType": null, "articleType": null, "__typename": "ContentIdentity"}, "articleSection": {"internal": [{"url": {"canonical": "https://www.economist.com/europe/", "__typename": "URL"}, "__typename": "Content", "headline": "Europe", "tegID": "75ks360ifh4d6k3c3n17b7s7uqcvb61a"}], "__typename": "Taxonomies"}, "publication": [{"headline": "WEEKLY EDITION: MAR 2ND 2024", "url": {"canonical": "https://www.economist.com/printedition/2024-03-02", "__typename": "URL"}, "__typename": "Content", "tegID": "j719mr4brfrmovgpemhjfldmmo3cg353"}, {"headline": "WEEKLY EDITION: MAR 2ND 2024", "url": {"canonical": "https://www.economist.com/eu/printedition/2024-03-02", "__typename": "URL"}, "__typename": "Content", "tegID": "c8e03oqtmf88qosaeavni6do2b3qp7t4"}, {"headline": "WEEKLY EDITION: MAR 2ND 2024", "url": {"canonical": "https://www.economist.com/ap/printedition/2024-03-02", "__typename": "URL"}, "__typename": "Content", "tegID": "jhnack3g4lmfqld87qn5qkj9v0m5h8qc"}, {"headline": "WEEKLY EDITION: MAR 2ND 2024", "url": {"canonical": "https://www.economist.com/la/printedition/2024-03-02", "__typename": "URL"}, "__typename": "Content", "tegID": "3l7slvo89iioeimngqiosm3ogebqdknv"}, {"headline": "WEEKLY EDITION: MAR 2ND 2024", "url": {"canonical": "https://www.economist.com/me/printedition/2024-03-02", "__typename": "URL"}, "__typename": "Content", "tegID": "i8cbko3s9k1rftrspvilocug59dv5ou6"}, {"headline": "WEEKLY EDITION: MAR 2ND 2024", "url": {"canonical": "https://www.economist.com/uk/printedition/2024-03-02", "__typename": "URL"}, "__typename": "Content", "tegID": "nphn7628rfcto0pgpeg2gce0e023fm7h"}, {"headline": "WEEKLY EDITION: MAR 2ND 2024", "url": {"canonical": "https://www.economist.com/na/printedition/2024-03-02", "__typename": "URL"}, "__typename": "Content", "tegID": "reeoom14ks2v3cnlekl593kvrldi9kak"}, {"headline": "WEEKLY EDITION: MAR 2ND 2024", "url": {"canonical": "https://www.economist.com/a/printedition/2024-03-02", "__typename": "URL"}, "__typename": "Content", "tegID": "5ga9s0u1etdqmbcbmos3rp9tudhevom8"}], "channel": {"tegID": "j53t6hsedat4l7rkbb1le98u73262sh5", "__typename": "Content"}, "headline": "Kharkiv is struggling under Russian rocket attacks", "subheadline": "Within range", "datePublished": "2024-02-26T17:03:43Z", "description": "A border region liberated by Ukraine\u2019s army faces a new onslaught", "image": {"main": {"url": {"canonical": "https://www.economist.com/media-assets/image/20240302_EUP502.jpg", "__typename": "URL"}, "__typename": "Content", "width": 1280, "height": 720}, "__typename": "Media", "promo": null}}], "__typename": "HasPart"}}], "__typename": "Taxonomies"}, "publication": [{"url": {"canonical": "https://www.economist.com/printedition/2024-03-02", "__typename": "URL"}, "__typename": "Content", "type": ["PublicationIssue"], "headline": "WEEKLY EDITION: MAR 2ND 2024", "description": "", "subheadline": "", "datePublished": "2024-03-02T00:00:00Z", "datePublishedString": "Mar 2nd 2024", "id": "/content/j719mr4brfrmovgpemhjfldmmo3cg353", "tegID": "j719mr4brfrmovgpemhjfldmmo3cg353", "image": {"cover": [{"url": {"canonical": "https://www.economist.com/media-assets/image/20240302_DE_US.jpg", "__typename": "URL"}, "__typename": "Content", "headline": "How high can markets go?", "width": 1280, "height": 1684, "regionsAllowed": ["US", "CA", "PM", "UM", "AI", "BL", "BQ", "BV", "CW", "GS", "MF", "SX", "AG", "AR", "AW", "BS", "BB", "BZ", "BM", "BO", "BR", "KY", "CL", "CO", "CR", "CU", "DM", "DO", "EC", "SV", "FK", "GF", "GD", "GP", "GT", "GY", "HN", "HT", "JM", "MQ", "MX", "MS", "NI", "PA", "PY", "PE", "PR", "KN", "LC", "VC", "SR", "TT", "TC", "UY", "VE", "VG", "VI"]}, {"url": {"canonical": "https://www.economist.com/media-assets/image/20240302_DE_EU.jpg", "__typename": "URL"}, "__typename": "Content", "headline": "How high can markets go?", "width": 1280, "height": 1684, "regionsAllowed": ["AD", "AL", "AM", "AX", "AZ", "BA", "BG", "BY", "CH", "CY", "CZ", "EE", "FO", "GE", "GI", "GL", "HR", "HU", "IS", "KG", "KZ", "LI", "LT", "LV", "MC", "MD", "ME", "MK", "MT", "NO", "PL", "RO", "RS", "RU", "SI", "SJ", "SK", "SM", "TJ", "TM", "TR", "UA", "UZ", "VA", "IT", "FR", "ES", "IE", "AT", "BE", "DK", "FI", "DE", "GR", "LU", "NL", "PT", "SE", "BH", "IR", "IQ", "IL", "JO", "KW", "LB", "OM", "SA", "SY", "AE", "PS", "QA", "YE", "DZ", "AO", "BJ", "BW", "BF", "BI", "CM", "CV", "CF", "TD", "KM", "CD", "CI", "DJ", "EG", "GQ", "ER", "ET", "GA", "GM", "GH", "GN", "GW", "KE", "LS", "LR", "LY", "MG", "MU", "MW", "ML", "MR", "YT", "MA", "MZ", "NA", "NE", "NG", "RE", "RW", "SH", "SS", "ST", "SN", "SL", "SO", "ZA", "SD", "SZ", "TZ", "TG", "TN", "UG", "EH", "ZM", "ZW", "CG"]}, {"url": {"canonical": "https://www.economist.com/media-assets/image/20240302_DE_AP.jpg", "__typename": "URL"}, "__typename": "Content", "headline": "India\u2019s north-south divide", "width": 1280, "height": 1684, "regionsAllowed": ["AF", "AS", "AU", "BD", "BT", "BN", "KH", "CN", "CK", "FJ", "GU", "PF", "HK", "IN", "ID", "JP", "KI", "KP", "KR", "LA", "MO", "MY", "MV", "MH", "FM", "MN", "MM", "NR", "NP", "NC", "NZ", "PK", "PG", "PH", "PN", "SC", "SG", "SB", "LK", "TF", "TW", "TH", "TO", "TV", "VU", "VN", "IO", "CC", "TL", "HM", "NU", "NF", "MP", "PW", "WS", "CX", "TK", "WF"]}, {"url": {"canonical": "https://www.economist.com/media-assets/image/20240302_DE_EU.jpg", "__typename": "URL"}, "__typename": "Content", "headline": "How high can markets go?", "width": 1280, "height": 1684, "regionsAllowed": ["AD", "AL", "AM", "AX", "AZ", "BA", "BG", "BY", "CH", "CY", "CZ", "EE", "FO", "GE", "GI", "GL", "HR", "HU", "IS", "KG", "KZ", "LI", "LT", "LV", "MC", "MD", "ME", "MK", "MT", "NO", "PL", "RO", "RS", "RU", "SI", "SJ", "SK", "SM", "TJ", "TM", "TR", "UA", "UZ", "VA", "IT", "FR", "ES", "IE", "AT", "BE", "DK", "FI", "DE", "GR", "LU", "NL", "PT", "SE", "BH", "IR", "IQ", "IL", "JO", "KW", "LB", "OM", "SA", "SY", "AE", "PS", "QA", "YE", "DZ", "AO", "BJ", "BW", "BF", "BI", "CM", "CV", "CF", "TD", "KM", "CD", "CI", "DJ", "EG", "GQ", "ER", "ET", "GA", "GM", "GH", "GN", "GW", "KE", "LS", "LR", "LY", "MG", "MU", "MW", "ML", "MR", "YT", "MA", "MZ", "NA", "NE", "NG", "RE", "RW", "SH", "SS", "ST", "SN", "SL", "SO", "ZA", "SD", "SZ", "TZ", "TG", "TN", "UG", "EH", "ZM", "ZW", "CG"]}, {"url": {"canonical": "https://www.economist.com/media-assets/image/20240302_DE_UK.jpg", "__typename": "URL"}, "__typename": "Content", "headline": "Build a British voter: Our new model for understanding the electorate", "width": 1280, "height": 1684, "regionsAllowed": ["UK", "GB", "GG", "IM", "JE"]}, {"url": {"canonical": "https://www.economist.com/media-assets/image/20240302_DE_US.jpg", "__typename": "URL"}, "__typename": "Content", "headline": "How high can markets go?", "width": 1280, "height": 1684, "regionsAllowed": ["US", "CA", "PM", "UM", "AI", "BL", "BQ", "BV", "CW", "GS", "MF", "SX", "AG", "AR", "AW", "BS", "BB", "BZ", "BM", "BO", "BR", "KY", "CL", "CO", "CR", "CU", "DM", "DO", "EC", "SV", "FK", "GF", "GD", "GP", "GT", "GY", "HN", "HT", "JM", "MQ", "MX", "MS", "NI", "PA", "PY", "PE", "PR", "KN", "LC", "VC", "SR", "TT", "TC", "UY", "VE", "VG", "VI"]}, {"url": {"canonical": "https://www.economist.com/media-assets/image/20240302_DE_EU.jpg", "__typename": "URL"}, "__typename": "Content", "headline": "How high can markets go?", "width": 1280, "height": 1684, "regionsAllowed": ["AD", "AL", "AM", "AX", "AZ", "BA", "BG", "BY", "CH", "CY", "CZ", "EE", "FO", "GE", "GI", "GL", "HR", "HU", "IS", "KG", "KZ", "LI", "LT", "LV", "MC", "MD", "ME", "MK", "MT", "NO", "PL", "RO", "RS", "RU", "SI", "SJ", "SK", "SM", "TJ", "TM", "TR", "UA", "UZ", "VA", "IT", "FR", "ES", "IE", "AT", "BE", "DK", "FI", "DE", "GR", "LU", "NL", "PT", "SE", "BH", "IR", "IQ", "IL", "JO", "KW", "LB", "OM", "SA", "SY", "AE", "PS", "QA", "YE", "DZ", "AO", "BJ", "BW", "BF", "BI", "CM", "CV", "CF", "TD", "KM", "CD", "CI", "DJ", "EG", "GQ", "ER", "ET", "GA", "GM", "GH", "GN", "GW", "KE", "LS", "LR", "LY", "MG", "MU", "MW", "ML", "MR", "YT", "MA", "MZ", "NA", "NE", "NG", "RE", "RW", "SH", "SS", "ST", "SN", "SL", "SO", "ZA", "SD", "SZ", "TZ", "TG", "TN", "UG", "EH", "ZM", "ZW", "CG"]}], "main": {"url": {"canonical": "https://www.economist.com/media-assets/image/20240302_DE_US.jpg", "__typename": "URL"}, "__typename": "Content", "width": 1280, "height": 1684}, "squareCover": [{"url": {"canonical": "https://www.economist.com/media-assets/image/20240302_DE_SQ_EU.jpg", "__typename": "URL"}, "__typename": "Content", "width": 1280, "height": 1280}, {"url": {"canonical": "https://www.economist.com/media-assets/image/20240302_DE_SQ_AP.jpg", "__typename": "URL"}, "__typename": "Content", "width": 1280, "height": 1422}, {"url": {"canonical": "https://www.economist.com/media-assets/image/20240302_DE_SQ_EU.jpg", "__typename": "URL"}, "__typename": "Content", "width": 1280, "height": 1280}, {"url": {"canonical": "https://www.economist.com/media-assets/image/20240302_DE_SQ_UK.jpg", "__typename": "URL"}, "__typename": "Content", "width": 1280, "height": 1422}, {"url": {"canonical": "https://www.economist.com/media-assets/image/20240302_DE_SQ_US.jpg", "__typename": "URL"}, "__typename": "Content", "width": 1280, "height": 1280}, {"url": {"canonical": "https://www.economist.com/media-assets/image/20240302_DE_SQ_EU.jpg", "__typename": "URL"}, "__typename": "Content", "width": 1280, "height": 1280}], "__typename": "Media"}}, {"url": {"canonical": "https://www.economist.com/eu/printedition/2024-03-02", "__typename": "URL"}, "__typename": "Content", "type": ["PublicationIssue", "RegionalIssue"], "headline": "WEEKLY EDITION: MAR 2ND 2024", "description": "", "subheadline": "", "datePublished": "2024-03-02T00:00:00Z", "datePublishedString": "Mar 2nd 2024", "id": "/content/c8e03oqtmf88qosaeavni6do2b3qp7t4", "tegID": "c8e03oqtmf88qosaeavni6do2b3qp7t4", "image": {"cover": [{"url": {"canonical": "https://www.economist.com/media-assets/image/20240302_DE_EU.jpg", "__typename": "URL"}, "__typename": "Content", "headline": "How high can markets go?", "width": 1280, "height": 1684, "regionsAllowed": ["AD", "AL", "AM", "AX", "AZ", "BA", "BG", "BY", "CH", "CY", "CZ", "EE", "FO", "GE", "GI", "GL", "HR", "HU", "IS", "KG", "KZ", "LI", "LT", "LV", "MC", "MD", "ME", "MK", "MT", "NO", "PL", "RO", "RS", "RU", "SI", "SJ", "SK", "SM", "TJ", "TM", "TR", "UA", "UZ", "VA", "IT", "FR", "ES", "IE", "AT", "BE", "DK", "FI", "DE", "GR", "LU", "NL", "PT", "SE", "BH", "IR", "IQ", "IL", "JO", "KW", "LB", "OM", "SA", "SY", "AE", "PS", "QA", "YE", "DZ", "AO", "BJ", "BW", "BF", "BI", "CM", "CV", "CF", "TD", "KM", "CD", "CI", "DJ", "EG", "GQ", "ER", "ET", "GA", "GM", "GH", "GN", "GW", "KE", "LS", "LR", "LY", "MG", "MU", "MW", "ML", "MR", "YT", "MA", "MZ", "NA", "NE", "NG", "RE", "RW", "SH", "SS", "ST", "SN", "SL", "SO", "ZA", "SD", "SZ", "TZ", "TG", "TN", "UG", "EH", "ZM", "ZW", "CG"]}], "main": {"url": {"canonical": "https://www.economist.com/media-assets/image/20240302_DE_EU.jpg", "__typename": "URL"}, "__typename": "Content", "width": 1280, "height": 1684}, "squareCover": [{"url": {"canonical": "https://www.economist.com/media-assets/image/20240302_DE_SQ_EU.jpg", "__typename": "URL"}, "__typename": "Content", "width": 1280, "height": 1280}], "__typename": "Media"}}, {"url": {"canonical": "https://www.economist.com/ap/printedition/2024-03-02", "__typename": "URL"}, "__typename": "Content", "type": ["PublicationIssue", "RegionalIssue"], "headline": "WEEKLY EDITION: MAR 2ND 2024", "description": "", "subheadline": "", "datePublished": "2024-03-02T00:00:00Z", "datePublishedString": "Mar 2nd 2024", "id": "/content/jhnack3g4lmfqld87qn5qkj9v0m5h8qc", "tegID": "jhnack3g4lmfqld87qn5qkj9v0m5h8qc", "image": {"cover": [{"url": {"canonical": "https://www.economist.com/media-assets/image/20240302_DE_AP.jpg", "__typename": "URL"}, "__typename": "Content", "headline": "India\u2019s north-south divide", "width": 1280, "height": 1684, "regionsAllowed": ["AF", "AS", "AU", "BD", "BT", "BN", "KH", "CN", "CK", "FJ", "GU", "PF", "HK", "IN", "ID", "JP", "KI", "KP", "KR", "LA", "MO", "MY", "MV", "MH", "FM", "MN", "MM", "NR", "NP", "NC", "NZ", "PK", "PG", "PH", "PN", "SC", "SG", "SB", "LK", "TF", "TW", "TH", "TO", "TV", "VU", "VN", "IO", "CC", "TL", "HM", "NU", "NF", "MP", "PW", "WS", "CX", "TK", "WF"]}], "main": {"url": {"canonical": "https://www.economist.com/media-assets/image/20240302_DE_AP.jpg", "__typename": "URL"}, "__typename": "Content", "width": 1280, "height": 1684}, "squareCover": [{"url": {"canonical": "https://www.economist.com/media-assets/image/20240302_DE_SQ_AP.jpg", "__typename": "URL"}, "__typename": "Content", "width": 1280, "height": 1422}], "__typename": "Media"}}, {"url": {"canonical": "https://www.economist.com/la/printedition/2024-03-02", "__typename": "URL"}, "__typename": "Content", "type": ["PublicationIssue", "RegionalIssue"], "headline": "WEEKLY EDITION: MAR 2ND 2024", "description": "", "subheadline": "", "datePublished": "2024-03-02T00:00:00Z", "datePublishedString": "Mar 2nd 2024", "id": "/content/3l7slvo89iioeimngqiosm3ogebqdknv", "tegID": "3l7slvo89iioeimngqiosm3ogebqdknv", "image": {"cover": [{"url": {"canonical": "https://www.economist.com/media-assets/image/20240302_DE_US.jpg", "__typename": "URL"}, "__typename": "Content", "headline": "How high can markets go?", "width": 1280, "height": 1684, "regionsAllowed": ["US", "CA", "PM", "UM", "AI", "BL", "BQ", "BV", "CW", "GS", "MF", "SX", "AG", "AR", "AW", "BS", "BB", "BZ", "BM", "BO", "BR", "KY", "CL", "CO", "CR", "CU", "DM", "DO", "EC", "SV", "FK", "GF", "GD", "GP", "GT", "GY", "HN", "HT", "JM", "MQ", "MX", "MS", "NI", "PA", "PY", "PE", "PR", "KN", "LC", "VC", "SR", "TT", "TC", "UY", "VE", "VG", "VI"]}], "main": {"url": {"canonical": "https://www.economist.com/media-assets/image/20240302_DE_US.jpg", "__typename": "URL"}, "__typename": "Content", "width": 1280, "height": 1684}, "squareCover": [{"url": {"canonical": "https://www.economist.com/media-assets/image/20240302_DE_SQ_US.jpg", "__typename": "URL"}, "__typename": "Content", "width": 1280, "height": 1280}], "__typename": "Media"}}, {"url": {"canonical": "https://www.economist.com/me/printedition/2024-03-02", "__typename": "URL"}, "__typename": "Content", "type": ["PublicationIssue", "RegionalIssue"], "headline": "WEEKLY EDITION: MAR 2ND 2024", "description": "", "subheadline": "", "datePublished": "2024-03-02T00:00:00Z", "datePublishedString": "Mar 2nd 2024", "id": "/content/i8cbko3s9k1rftrspvilocug59dv5ou6", "tegID": "i8cbko3s9k1rftrspvilocug59dv5ou6", "image": {"cover": [{"url": {"canonical": "https://www.economist.com/media-assets/image/20240302_DE_EU.jpg", "__typename": "URL"}, "__typename": "Content", "headline": "How high can markets go?", "width": 1280, "height": 1684, "regionsAllowed": ["AD", "AL", "AM", "AX", "AZ", "BA", "BG", "BY", "CH", "CY", "CZ", "EE", "FO", "GE", "GI", "GL", "HR", "HU", "IS", "KG", "KZ", "LI", "LT", "LV", "MC", "MD", "ME", "MK", "MT", "NO", "PL", "RO", "RS", "RU", "SI", "SJ", "SK", "SM", "TJ", "TM", "TR", "UA", "UZ", "VA", "IT", "FR", "ES", "IE", "AT", "BE", "DK", "FI", "DE", "GR", "LU", "NL", "PT", "SE", "BH", "IR", "IQ", "IL", "JO", "KW", "LB", "OM", "SA", "SY", "AE", "PS", "QA", "YE", "DZ", "AO", "BJ", "BW", "BF", "BI", "CM", "CV", "CF", "TD", "KM", "CD", "CI", "DJ", "EG", "GQ", "ER", "ET", "GA", "GM", "GH", "GN", "GW", "KE", "LS", "LR", "LY", "MG", "MU", "MW", "ML", "MR", "YT", "MA", "MZ", "NA", "NE", "NG", "RE", "RW", "SH", "SS", "ST", "SN", "SL", "SO", "ZA", "SD", "SZ", "TZ", "TG", "TN", "UG", "EH", "ZM", "ZW", "CG"]}], "main": {"url": {"canonical": "https://www.economist.com/media-assets/image/20240302_DE_EU.jpg", "__typename": "URL"}, "__typename": "Content", "width": 1280, "height": 1684}, "squareCover": [{"url": {"canonical": "https://www.economist.com/media-assets/image/20240302_DE_SQ_EU.jpg", "__typename": "URL"}, "__typename": "Content", "width": 1280, "height": 1280}], "__typename": "Media"}}, {"url": {"canonical": "https://www.economist.com/uk/printedition/2024-03-02", "__typename": "URL"}, "__typename": "Content", "type": ["PublicationIssue", "RegionalIssue"], "headline": "WEEKLY EDITION: MAR 2ND 2024", "description": "", "subheadline": "", "datePublished": "2024-03-02T00:00:00Z", "datePublishedString": "Mar 2nd 2024", "id": "/content/nphn7628rfcto0pgpeg2gce0e023fm7h", "tegID": "nphn7628rfcto0pgpeg2gce0e023fm7h", "image": {"cover": [{"url": {"canonical": "https://www.economist.com/media-assets/image/20240302_DE_UK.jpg", "__typename": "URL"}, "__typename": "Content", "headline": "Build a British voter: Our new model for understanding the electorate", "width": 1280, "height": 1684, "regionsAllowed": ["UK", "GB", "GG", "IM", "JE"]}], "main": {"url": {"canonical": "https://www.economist.com/media-assets/image/20240302_DE_UK.jpg", "__typename": "URL"}, "__typename": "Content", "width": 1280, "height": 1684}, "squareCover": [{"url": {"canonical": "https://www.economist.com/media-assets/image/20240302_DE_SQ_UK.jpg", "__typename": "URL"}, "__typename": "Content", "width": 1280, "height": 1422}], "__typename": "Media"}}, {"url": {"canonical": "https://www.economist.com/na/printedition/2024-03-02", "__typename": "URL"}, "__typename": "Content", "type": ["PublicationIssue", "RegionalIssue"], "headline": "WEEKLY EDITION: MAR 2ND 2024", "description": "", "subheadline": "", "datePublished": "2024-03-02T00:00:00Z", "datePublishedString": "Mar 2nd 2024", "id": "/content/reeoom14ks2v3cnlekl593kvrldi9kak", "tegID": "reeoom14ks2v3cnlekl593kvrldi9kak", "image": {"cover": [{"url": {"canonical": "https://www.economist.com/media-assets/image/20240302_DE_US.jpg", "__typename": "URL"}, "__typename": "Content", "headline": "How high can markets go?", "width": 1280, "height": 1684, "regionsAllowed": ["US", "CA", "PM", "UM", "AI", "BL", "BQ", "BV", "CW", "GS", "MF", "SX", "AG", "AR", "AW", "BS", "BB", "BZ", "BM", "BO", "BR", "KY", "CL", "CO", "CR", "CU", "DM", "DO", "EC", "SV", "FK", "GF", "GD", "GP", "GT", "GY", "HN", "HT", "JM", "MQ", "MX", "MS", "NI", "PA", "PY", "PE", "PR", "KN", "LC", "VC", "SR", "TT", "TC", "UY", "VE", "VG", "VI"]}], "main": {"url": {"canonical": "https://www.economist.com/media-assets/image/20240302_DE_US.jpg", "__typename": "URL"}, "__typename": "Content", "width": 1280, "height": 1684}, "squareCover": [{"url": {"canonical": "https://www.economist.com/media-assets/image/20240302_DE_SQ_US.jpg", "__typename": "URL"}, "__typename": "Content", "width": 1280, "height": 1280}], "__typename": "Media"}}, {"url": {"canonical": "https://www.economist.com/a/printedition/2024-03-02", "__typename": "URL"}, "__typename": "Content", "type": ["PublicationIssue", "RegionalIssue"], "headline": "WEEKLY EDITION: MAR 2ND 2024", "description": "", "subheadline": "", "datePublished": "2024-03-02T00:00:00Z", "datePublishedString": "Mar 2nd 2024", "id": "/content/5ga9s0u1etdqmbcbmos3rp9tudhevom8", "tegID": "5ga9s0u1etdqmbcbmos3rp9tudhevom8", "image": {"cover": [{"url": {"canonical": "https://www.economist.com/media-assets/image/20240302_DE_EU.jpg", "__typename": "URL"}, "__typename": "Content", "headline": "How high can markets go?", "width": 1280, "height": 1684, "regionsAllowed": ["AD", "AL", "AM", "AX", "AZ", "BA", "BG", "BY", "CH", "CY", "CZ", "EE", "FO", "GE", "GI", "GL", "HR", "HU", "IS", "KG", "KZ", "LI", "LT", "LV", "MC", "MD", "ME", "MK", "MT", "NO", "PL", "RO", "RS", "RU", "SI", "SJ", "SK", "SM", "TJ", "TM", "TR", "UA", "UZ", "VA", "IT", "FR", "ES", "IE", "AT", "BE", "DK", "FI", "DE", "GR", "LU", "NL", "PT", "SE", "BH", "IR", "IQ", "IL", "JO", "KW", "LB", "OM", "SA", "SY", "AE", "PS", "QA", "YE", "DZ", "AO", "BJ", "BW", "BF", "BI", "CM", "CV", "CF", "TD", "KM", "CD", "CI", "DJ", "EG", "GQ", "ER", "ET", "GA", "GM", "GH", "GN", "GW", "KE", "LS", "LR", "LY", "MG", "MU", "MW", "ML", "MR", "YT", "MA", "MZ", "NA", "NE", "NG", "RE", "RW", "SH", "SS", "ST", "SN", "SL", "SO", "ZA", "SD", "SZ", "TZ", "TG", "TN", "UG", "EH", "ZM", "ZW", "CG"]}], "main": {"url": {"canonical": "https://www.economist.com/media-assets/image/20240302_DE_EU.jpg", "__typename": "URL"}, "__typename": "Content", "width": 1280, "height": 1684}, "squareCover": [{"url": {"canonical": "https://www.economist.com/media-assets/image/20240302_DE_SQ_EU.jpg", "__typename": "URL"}, "__typename": "Content", "width": 1280, "height": 1280}], "__typename": "Media"}}], "channel": {"tegID": "j53t6hsedat4l7rkbb1le98u73262sh5", "__typename": "Content"}, "_metadata": {"articleId": "/content/3n1gbd1p1akeb02nlhd7vn4a9aomq3q1", "tegID": "3n1gbd1p1akeb02nlhd7vn4a9aomq3q1", "title": "Charlemagne - Is Europe\u2019s stubby skyline a sign of low ambition? | Europe | The Economist", "shareSnippet": "Charlemagne \u2013 Is Europe\u2019s stubby skyline a sign of low ambition?", "headline": "Is Europe\u2019s stubby skyline a sign of low ambition?", "section": "Europe", "keywords": [], "author": ["The Economist"], "url": "https://www.economist.com/europe/2024/02/28/is-europes-lack-of-skyscapers-a-blessing-or-a-sign-of-deficient-ambition", "type": "Article", "articleBody": "", "description": "Only seven of the world\u2019s 1,000 tallest buildings are in the EU", "ogDescription": "Only seven of the world\u2019s 1,000 tallest buildings are in the EU", "imageUrl": "https://www.economist.com/media-assets/image/20240302_EUD000.jpg", "imageHeight": 720, "imageWidth": 1280, "datePublished": "2024-02-28T19:25:20Z", "dateModified": "2024-02-29T19:08:32Z", "dateCreated": "2024-02-28T14:23:22Z", "isPrintArticle": true, "printEdition": "2024-03-02T00:00:00Z", "copyrightYear": 2024, "dateline": "", "inLanguage": "en", "interactive": false, "scripts": [], "css": []}, "sectionArticles": [{"id": "/content/2ggkfs0jmaoto8455v6kp9j3dngkdpvb", "publication": [{"id": "/content/j719mr4brfrmovgpemhjfldmmo3cg353", "context": {"position": 1100.22, "__typename": "Content"}, "__typename": "Content"}, {"id": "/content/c8e03oqtmf88qosaeavni6do2b3qp7t4", "context": {"position": 450.22, "__typename": "Content"}, "__typename": "Content"}, {"id": "/content/jhnack3g4lmfqld87qn5qkj9v0m5h8qc", "context": {"position": 1100.22, "__typename": "Content"}, "__typename": "Content"}, {"id": "/content/3l7slvo89iioeimngqiosm3ogebqdknv", "context": {"position": 1100.22, "__typename": "Content"}, "__typename": "Content"}, {"id": "/content/i8cbko3s9k1rftrspvilocug59dv5ou6", "context": {"position": 450.22, "__typename": "Content"}, "__typename": "Content"}, {"id": "/content/nphn7628rfcto0pgpeg2gce0e023fm7h", "context": {"position": 460.22, "__typename": "Content"}, "__typename": "Content"}, {"id": "/content/reeoom14ks2v3cnlekl593kvrldi9kak", "context": {"position": 1100.22, "__typename": "Content"}, "__typename": "Content"}, {"id": "/content/5ga9s0u1etdqmbcbmos3rp9tudhevom8", "context": {"position": 450.22, "__typename": "Content"}, "__typename": "Content"}], "headline": "France and Germany are at loggerheads over military aid to Ukraine", "url": {"canonical": "https://www.economist.com/europe/2024/02/29/france-and-germany-are-at-loggerheads-over-military-aid-to-ukraine", "__typename": "URL"}, "__typename": "Content"}, {"id": "/content/4l5n9rquk0j0r4ak2qrchn772fks2oue", "publication": [{"id": "/content/j719mr4brfrmovgpemhjfldmmo3cg353", "context": {"position": 1100.23, "__typename": "Content"}, "__typename": "Content"}, {"id": "/content/c8e03oqtmf88qosaeavni6do2b3qp7t4", "context": {"position": 450.23, "__typename": "Content"}, "__typename": "Content"}, {"id": "/content/jhnack3g4lmfqld87qn5qkj9v0m5h8qc", "context": {"position": 1100.23, "__typename": "Content"}, "__typename": "Content"}, {"id": "/content/3l7slvo89iioeimngqiosm3ogebqdknv", "context": {"position": 1100.23, "__typename": "Content"}, "__typename": "Content"}, {"id": "/content/i8cbko3s9k1rftrspvilocug59dv5ou6", "context": {"position": 450.23, "__typename": "Content"}, "__typename": "Content"}, {"id": "/content/nphn7628rfcto0pgpeg2gce0e023fm7h", "context": {"position": 460.23, "__typename": "Content"}, "__typename": "Content"}, {"id": "/content/reeoom14ks2v3cnlekl593kvrldi9kak", "context": {"position": 1100.23, "__typename": "Content"}, "__typename": "Content"}, {"id": "/content/5ga9s0u1etdqmbcbmos3rp9tudhevom8", "context": {"position": 450.23, "__typename": "Content"}, "__typename": "Content"}], "headline": "Europe hopes barbed wire will keep migrants out. It won\u2019t", "url": {"canonical": "https://www.economist.com/europe/2024/02/29/europe-hopes-barbed-wire-will-keep-migrants-out-it-wont", "__typename": "URL"}, "__typename": "Content"}, {"id": "/content/prq002j35qkrc5lrqpkgrmk8lfjpmpc6", "publication": [{"id": "/content/j719mr4brfrmovgpemhjfldmmo3cg353", "context": {"position": 1100.24, "__typename": "Content"}, "__typename": "Content"}, {"id": "/content/c8e03oqtmf88qosaeavni6do2b3qp7t4", "context": {"position": 450.24, "__typename": "Content"}, "__typename": "Content"}, {"id": "/content/jhnack3g4lmfqld87qn5qkj9v0m5h8qc", "context": {"position": 1100.24, "__typename": "Content"}, "__typename": "Content"}, {"id": "/content/3l7slvo89iioeimngqiosm3ogebqdknv", "context": {"position": 1100.24, "__typename": "Content"}, "__typename": "Content"}, {"id": "/content/i8cbko3s9k1rftrspvilocug59dv5ou6", "context": {"position": 450.24, "__typename": "Content"}, "__typename": "Content"}, {"id": "/content/nphn7628rfcto0pgpeg2gce0e023fm7h", "context": {"position": 460.24, "__typename": "Content"}, "__typename": "Content"}, {"id": "/content/reeoom14ks2v3cnlekl593kvrldi9kak", "context": {"position": 1100.24, "__typename": "Content"}, "__typename": "Content"}, {"id": "/content/5ga9s0u1etdqmbcbmos3rp9tudhevom8", "context": {"position": 450.24, "__typename": "Content"}, "__typename": "Content"}], "headline": "Azerbaijan is racing to rebuild in recaptured Nagorno-Karabakh", "url": {"canonical": "https://www.economist.com/europe/2024/02/29/azerbaijan-is-racing-to-rebuild-in-recaptured-nagorno-karabakh", "__typename": "URL"}, "__typename": "Content"}, {"id": "/content/3n1gbd1p1akeb02nlhd7vn4a9aomq3q1", "publication": [{"id": "/content/j719mr4brfrmovgpemhjfldmmo3cg353", "context": {"position": 1100.26, "__typename": "Content"}, "__typename": "Content"}, {"id": "/content/c8e03oqtmf88qosaeavni6do2b3qp7t4", "context": {"position": 450.26, "__typename": "Content"}, "__typename": "Content"}, {"id": "/content/jhnack3g4lmfqld87qn5qkj9v0m5h8qc", "context": {"position": 1100.26, "__typename": "Content"}, "__typename": "Content"}, {"id": "/content/3l7slvo89iioeimngqiosm3ogebqdknv", "context": {"position": 1100.26, "__typename": "Content"}, "__typename": "Content"}, {"id": "/content/i8cbko3s9k1rftrspvilocug59dv5ou6", "context": {"position": 450.26, "__typename": "Content"}, "__typename": "Content"}, {"id": "/content/nphn7628rfcto0pgpeg2gce0e023fm7h", "context": {"position": 460.26, "__typename": "Content"}, "__typename": "Content"}, {"id": "/content/reeoom14ks2v3cnlekl593kvrldi9kak", "context": {"position": 1100.26, "__typename": "Content"}, "__typename": "Content"}, {"id": "/content/5ga9s0u1etdqmbcbmos3rp9tudhevom8", "context": {"position": 450.26, "__typename": "Content"}, "__typename": "Content"}], "headline": "Is Europe\u2019s stubby skyline a sign of low ambition?", "url": {"canonical": "https://www.economist.com/europe/2024/02/28/is-europes-lack-of-skyscapers-a-blessing-or-a-sign-of-deficient-ambition", "__typename": "URL"}, "__typename": "Content"}, {"id": "/content/pc80jb0n782a5lmmoifjssujpmp6osr8", "publication": [{"id": "/content/j719mr4brfrmovgpemhjfldmmo3cg353", "context": {"position": 1100.25, "__typename": "Content"}, "__typename": "Content"}, {"id": "/content/c8e03oqtmf88qosaeavni6do2b3qp7t4", "context": {"position": 450.25, "__typename": "Content"}, "__typename": "Content"}, {"id": "/content/jhnack3g4lmfqld87qn5qkj9v0m5h8qc", "context": {"position": 1100.25, "__typename": "Content"}, "__typename": "Content"}, {"id": "/content/3l7slvo89iioeimngqiosm3ogebqdknv", "context": {"position": 1100.25, "__typename": "Content"}, "__typename": "Content"}, {"id": "/content/i8cbko3s9k1rftrspvilocug59dv5ou6", "context": {"position": 450.25, "__typename": "Content"}, "__typename": "Content"}, {"id": "/content/nphn7628rfcto0pgpeg2gce0e023fm7h", "context": {"position": 460.25, "__typename": "Content"}, "__typename": "Content"}, {"id": "/content/reeoom14ks2v3cnlekl593kvrldi9kak", "context": {"position": 1100.25, "__typename": "Content"}, "__typename": "Content"}, {"id": "/content/5ga9s0u1etdqmbcbmos3rp9tudhevom8", "context": {"position": 450.25, "__typename": "Content"}, "__typename": "Content"}], "headline": "Kharkiv is struggling under Russian rocket attacks", "url": {"canonical": "https://www.economist.com/europe/2024/02/26/kharkiv-is-struggling-under-russian-rocket-attacks", "__typename": "URL"}, "__typename": "Content"}, {"id": "/content/jm8ijrhtg9qujhngjolgn7pp1fb71917", "publication": [{"id": "/content/j719mr4brfrmovgpemhjfldmmo3cg353", "context": {"position": 1100.21, "__typename": "Content"}, "__typename": "Content"}, {"id": "/content/c8e03oqtmf88qosaeavni6do2b3qp7t4", "context": {"position": 450.21000000000004, "__typename": "Content"}, "__typename": "Content"}, {"id": "/content/jhnack3g4lmfqld87qn5qkj9v0m5h8qc", "context": {"position": 1100.21, "__typename": "Content"}, "__typename": "Content"}, {"id": "/content/3l7slvo89iioeimngqiosm3ogebqdknv", "context": {"position": 1100.21, "__typename": "Content"}, "__typename": "Content"}, {"id": "/content/i8cbko3s9k1rftrspvilocug59dv5ou6", "context": {"position": 450.21000000000004, "__typename": "Content"}, "__typename": "Content"}, {"id": "/content/nphn7628rfcto0pgpeg2gce0e023fm7h", "context": {"position": 460.21000000000004, "__typename": "Content"}, "__typename": "Content"}, {"id": "/content/reeoom14ks2v3cnlekl593kvrldi9kak", "context": {"position": 1100.21, "__typename": "Content"}, "__typename": "Content"}, {"id": "/content/5ga9s0u1etdqmbcbmos3rp9tudhevom8", "context": {"position": 450.21000000000004, "__typename": "Content"}, "__typename": "Content"}], "headline": "How Marine Le Pen is preparing for power", "url": {"canonical": "https://www.economist.com/europe/2024/02/25/how-marine-le-pen-is-preparing-for-power", "__typename": "URL"}, "__typename": "Content"}]}